phoneme_converter/__init__.py
phoneme_converter/converter.py
phoneme_converter-20250620.dist-info/licenses/LICENSE
phoneme_converter-20250620.dist-info/METADATA
phoneme_converter-20250620.dist-info/WHEEL
phoneme_converter-20250620.dist-info/top_level.txt
phoneme_converter-20250620.dist-info/RECORD
