Metadata-Version: 2.4
Name: phoneme-converter
Version: 20250620
Summary: Phoneme format converter for IPA arpa etc.
License: MIT license
Project-URL: Homepage, https://github.com/qiziAI/phoneme-converter
Requires-Python: >=3.7
License-File: LICENSE
Dynamic: license-file
